{"name":"Lv3","SubTexture":[{"name":"zhuti","x":1,"height":316,"y":1,"width":258},{"name":"eye1","x":55,"height":18,"y":489,"width":57},{"name":"eye2","x":199,"height":18,"y":339,"width":57},{"name":"eye3","x":199,"height":18,"y":319,"width":57},{"name":"shou1","x":120,"height":82,"y":319,"width":47},{"name":"shou2","x":120,"height":74,"y":403,"width":35},{"name":"shou3","x":169,"height":60,"y":319,"width":28},{"name":"toufa","x":182,"height":52,"y":381,"width":29},{"name":"xiong","x":1,"height":71,"y":319,"width":98},{"name":"hudiejie","x":1,"height":49,"y":448,"width":52},{"name":"shou5","x":157,"height":90,"y":403,"width":23},{"name":"shou4","x":55,"height":39,"y":448,"width":54},{"name":"panzi","x":1,"height":54,"y":392,"width":117}],"imagePath":"Lv3_tex.png","height":512,"width":512}